README.rst
setup.py
dj_elastictranscoder/__init__.py
dj_elastictranscoder/admin.py
dj_elastictranscoder/models.py
dj_elastictranscoder/signals.py
dj_elastictranscoder/transcoder.py
dj_elastictranscoder/urls.py
dj_elastictranscoder/views.py
dj_elastictranscoder/migrations/0001_initial.py
dj_elastictranscoder/migrations/__init__.py
dj_elastictranscoder/south_migrations/0001_initial.py
dj_elastictranscoder/south_migrations/__init__.py
django_elastic_transcoder_socialschools.egg-info/PKG-INFO
django_elastic_transcoder_socialschools.egg-info/SOURCES.txt
django_elastic_transcoder_socialschools.egg-info/dependency_links.txt
django_elastic_transcoder_socialschools.egg-info/not-zip-safe
django_elastic_transcoder_socialschools.egg-info/requires.txt
django_elastic_transcoder_socialschools.egg-info/top_level.txt
testsapp/__init__.py
testsapp/models.py
testsapp/test_job.py
testsapp/tests_settings.py